miko/__init__.py
miko/miko.cp38-win_amd64.pyd
miko/font/default.otf
mikoo-0.1.dist-info/LICENSE
mikoo-0.1.dist-info/METADATA
mikoo-0.1.dist-info/WHEEL
mikoo-0.1.dist-info/entry_points.txt
mikoo-0.1.dist-info/top_level.txt
mikoo-0.1.dist-info/RECORD
