Metadata-Version: 2.1
Name: mikoo
Version: 0.1
Summary: 加速实现AIGC、自动办公的中文编程工具
Home-page: https://www.mikooo.cn
Author: Milk
Author-email: 719496375@qq.com
License: The MIT License
Platform: UNKNOWN
Classifier: Programming Language :: Python :: 3
Classifier: License :: OSI Approved :: MIT License
Classifier: Operating System :: OS Independent
Requires-Dist: requests >=2.31.0
Requires-Dist: moviepy >=1.0.3
